jinpro/__init__.py
jinpro/jinpro.py
jinpro-1.0.1.dist-info/LICENSE
jinpro-1.0.1.dist-info/METADATA
jinpro-1.0.1.dist-info/WHEEL
jinpro-1.0.1.dist-info/top_level.txt
jinpro-1.0.1.dist-info/RECORD
