Metadata-Version: 2.1
Name: jinpro
Version: 1.0.1
Summary: A component preprocessor for Flask/Jinja that mimics React/Vue-style components
Home-page: https://github.com/sophloaf2019/jinpro
Author: Sophia Turner
Author-email: sophia-r-turner@protonmail.com
Classifier: Programming Language :: Python :: 3
Classifier: License :: OSI Approved :: GNU General Public License v3 (GPLv3)
Classifier: Operating System :: OS Independent
Requires-Python: >=3.6
License-File: LICENSE
Requires-Dist: Flask>=3
